tjquant/__init__.py
tjquant/client.ini.py
tjquant/client.py
tjquant/client_sqlite.py
tjquant/smtp_163.py
tjquant/demo/__init__.py
tjquant/demo/client_sqlite_demo.py
tjquant-3.0.1.dist-info/LICENSE
tjquant-3.0.1.dist-info/METADATA
tjquant-3.0.1.dist-info/WHEEL
tjquant-3.0.1.dist-info/top_level.txt
tjquant-3.0.1.dist-info/RECORD
