Metadata-Version: 2.1
Name: tjquant
Version: 3.0.1
Summary: Quant tools for TJU
Home-page: https://github.com/pypa/example-project
Author: TX. Chen
Author-email: 670683134@qq.com
License: UNKNOWN
Platform: UNKNOWN
Classifier: Programming Language :: Python :: 3
Classifier: License :: OSI Approved :: MIT License
Classifier: Operating System :: OS Independent
Classifier: Topic :: Office/Business :: Financial
